dbautomator/__init__.py
dbautomator/mongo_crud.py
dbautomator-0.0.2.data/data/requirements.txt
dbautomator-0.0.2.dist-info/METADATA
dbautomator-0.0.2.dist-info/WHEEL
dbautomator-0.0.2.dist-info/top_level.txt
dbautomator-0.0.2.dist-info/RECORD
